Metadata-Version: 2.1
Name: instareset
Version: 2.0.0
Summary: Send password reset requests to Instagram accounts without reCaptcha
Home-page: https://www.github.com/Kh4lidMD/InstaReset
Author: Khaled Mahmoud
Author-email: KhalidYBel@gmail.com
Classifier: Development Status :: 5 - Production/Stable
Classifier: Programming Language :: Python :: 3.7
Classifier: Programming Language :: Python :: 3.8
Classifier: Programming Language :: Python :: 3.9
Classifier: Programming Language :: Python :: 3.10
Classifier: Programming Language :: Python :: 3.11
Classifier: Programming Language :: Python :: 3.12
Classifier: Topic :: Software Development :: Libraries
Classifier: License :: OSI Approved :: MIT License
License-File: LICENSE
